{"status":"success","data":{"planet":{"id":"109","name":"Hexcavations \u03a9","description":"Find the correct path for the equations!","question_count":"10","badges":{"speed":"1","accuracy":"1","score_mul_base":"1","score_mul_accuracy":"1","score_mul_speed":"1"}},"status":{"star":2,"difficulty":3,"top_score":0},"planet_top_score":[],"questions":[{"id":"364376","param_1":"50","param_2":"-","param_3":"24","param_4":"+","param_5":"22","param_6":"=","param_7":"48","hexagon_path":"e","difficulty":"3"},{"id":"364378","param_1":"71","param_2":"-","param_3":"19","param_4":"+","param_5":"21","param_6":"=","param_7":"73","hexagon_path":"e","difficulty":"3"},{"id":"363620","param_1":"65","param_2":"-","param_3":"19","param_4":"+","param_5":"11","param_6":"=","param_7":"57","hexagon_path":"b","difficulty":"3"},{"id":"364375","param_1":"61","param_2":"-","param_3":"27","param_4":"+","param_5":"10","param_6":"=","param_7":"44","hexagon_path":"e","difficulty":"3"},{"id":"364146","param_1":"25","param_2":"-","param_3":"13","param_4":"+","param_5":"11","param_6":"=","param_7":"23","hexagon_path":"d","difficulty":"3"},{"id":"364393","param_1":"25","param_2":"-","param_3":"18","param_4":"+","param_5":"12","param_6":"=","param_7":"19","hexagon_path":"e","difficulty":"3"},{"id":"364851","param_1":"28","param_2":"+","param_3":"25","param_4":"-","param_5":"14","param_6":"=","param_7":"39","hexagon_path":"i","difficulty":"3"},{"id":"365118","param_1":"99","param_2":"+","param_3":"26","param_4":"-","param_5":"42","param_6":"=","param_7":"83","hexagon_path":"j","difficulty":"3"},{"id":"363628","param_1":"71","param_2":"-","param_3":"19","param_4":"+","param_5":"21","param_6":"=","param_7":"73","hexagon_path":"b","difficulty":"3"},{"id":"365143","param_1":"25","param_2":"-","param_3":"18","param_4":"+","param_5":"12","param_6":"=","param_7":"19","hexagon_path":"j","difficulty":"3"}]}}