{"status":"success","data":{"planet":{"id":"110","name":"Magic Mix","description":"Figure out the pattern!","question_count":"10","badges":{"speed":"1","accuracy":"1","score_mul_base":"1","score_mul_accuracy":"1","score_mul_speed":"1"}},"status":{"star":1,"difficulty":2,"top_score":0},"planet_top_score":[],"questions":[{"id":"349760","color_1":"G","number_1":"3","color_2":"G","number_2":"90","color_3":"B","number_3":"2","color_4":"B","number_4":"1","color_5":"Y","number_5":"3","color_6":"Y","number_6":"69","fake_color_1":"B","fake_number_1":"81","fake_color_2":"G","fake_number_2":"81","difficulty":"2"},{"id":"349785","color_1":"G","number_1":"1","color_2":"G","number_2":"65","color_3":"B","number_3":"4","color_4":"B","number_4":"8","color_5":"Y","number_5":"1","color_6":"Y","number_6":"17","fake_color_1":"B","fake_number_1":"60","fake_color_2":"G","fake_number_2":"60","difficulty":"2"},{"id":"349822","color_1":"P","number_1":"3","color_2":"P","number_2":"85","color_3":"R","number_3":"3","color_4":"R","number_4":"4","color_5":"B","number_5":"3","color_6":"B","number_6":"51","fake_color_1":"R","fake_number_1":"87","fake_color_2":"P","fake_number_2":"87","difficulty":"2"},{"id":"349797","color_1":"G","number_1":"4","color_2":"G","number_2":"42","color_3":"B","number_3":"7","color_4":"B","number_4":"2","color_5":"Y","number_5":"3","color_6":"Y","number_6":"70","fake_color_1":"B","fake_number_1":"98","fake_color_2":"G","fake_number_2":"98","difficulty":"2"},{"id":"349792","color_1":"G","number_1":"4","color_2":"G","number_2":"47","color_3":"B","number_3":"6","color_4":"B","number_4":"6","color_5":"Y","number_5":"3","color_6":"Y","number_6":"81","fake_color_1":"B","fake_number_1":"63","fake_color_2":"G","fake_number_2":"63","difficulty":"2"},{"id":"349761","color_1":"G","number_1":"3","color_2":"G","number_2":"89","color_3":"B","number_3":"2","color_4":"B","number_4":"2","color_5":"Y","number_5":"3","color_6":"Y","number_6":"67","fake_color_1":"B","fake_number_1":"25","fake_color_2":"G","fake_number_2":"25","difficulty":"2"},{"id":"349846","color_1":"P","number_1":"8","color_2":"P","number_2":"14","color_3":"R","number_3":"6","color_4":"R","number_4":"1","color_5":"B","number_5":"7","color_6":"B","number_6":"53","fake_color_1":"R","fake_number_1":"46","fake_color_2":"P","fake_number_2":"46","difficulty":"2"},{"id":"349791","color_1":"G","number_1":"4","color_2":"G","number_2":"48","color_3":"B","number_3":"6","color_4":"B","number_4":"5","color_5":"Y","number_5":"3","color_6":"Y","number_6":"83","fake_color_1":"B","fake_number_1":"50","fake_color_2":"G","fake_number_2":"50","difficulty":"2"},{"id":"349819","color_1":"P","number_1":"1","color_2":"P","number_2":"79","color_3":"R","number_3":"3","color_4":"R","number_4":"1","color_5":"B","number_5":"1","color_6":"B","number_6":"48","fake_color_1":"R","fake_number_1":"25","fake_color_2":"P","fake_number_2":"25","difficulty":"2"},{"id":"349810","color_1":"P","number_1":"5","color_2":"P","number_2":"93","color_3":"R","number_3":"2","color_4":"R","number_4":"1","color_5":"B","number_5":"5","color_6":"B","number_6":"72","fake_color_1":"R","fake_number_1":"25","fake_color_2":"P","fake_number_2":"25","difficulty":"2"}]}}