{"status":"success","data":{"planet":{"id":"129","name":"Rescue Line","description":"Identify the correct place on the line","question_count":"10","badges":{"speed":"1","accuracy":"1","score_mul_base":"1","score_mul_accuracy":"1","score_mul_speed":"1"}},"status":{"star":1,"difficulty":2,"top_score":0},"planet_top_score":[],"questions":[{"id":"211014","question":"4","option_from":"0","option_until_total":"20","answer":"4","ruler_type":"2","difficulty":"2"},{"id":"211022","question":"12","option_from":"0","option_until_total":"20","answer":"12","ruler_type":"2","difficulty":"2"},{"id":"211028","question":"18","option_from":"0","option_until_total":"20","answer":"18","ruler_type":"2","difficulty":"2"},{"id":"211011","question":"1","option_from":"0","option_until_total":"20","answer":"1","ruler_type":"2","difficulty":"2"},{"id":"211012","question":"2","option_from":"0","option_until_total":"20","answer":"2","ruler_type":"2","difficulty":"2"},{"id":"211029","question":"19","option_from":"0","option_until_total":"20","answer":"19","ruler_type":"2","difficulty":"2"},{"id":"211023","question":"13","option_from":"0","option_until_total":"20","answer":"13","ruler_type":"2","difficulty":"2"},{"id":"211027","question":"17","option_from":"0","option_until_total":"20","answer":"17","ruler_type":"2","difficulty":"2"},{"id":"211017","question":"7","option_from":"0","option_until_total":"20","answer":"7","ruler_type":"2","difficulty":"2"},{"id":"211021","question":"11","option_from":"0","option_until_total":"20","answer":"11","ruler_type":"2","difficulty":"2"}]}}