{"status":"success","data":{"planet":{"id":"117","name":"Tap Trouble","description":"Limited Breaks","question_count":"10","badges":{"speed":"1","accuracy":"1","score_mul_base":"1","score_mul_accuracy":"1","score_mul_speed":"1"}},"status":{"star":2,"difficulty":3,"top_score":0},"planet_top_score":[],"questions":[{"id":"230690","question":"890","answer":"890","option_type":"hundred","option_generate":"10","difficulty":"3"},{"id":"230795","question":"995","answer":"995","option_type":"hundred","option_generate":"10","difficulty":"3"},{"id":"230593","question":"793","answer":"793","option_type":"hundred","option_generate":"10","difficulty":"3"},{"id":"230775","question":"975","answer":"975","option_type":"hundred","option_generate":"10","difficulty":"3"},{"id":"230724","question":"924","answer":"924","option_type":"hundred","option_generate":"10","difficulty":"3"},{"id":"230512","question":"712","answer":"712","option_type":"hundred","option_generate":"10","difficulty":"3"},{"id":"230649","question":"849","answer":"849","option_type":"hundred","option_generate":"10","difficulty":"3"},{"id":"230526","question":"726","answer":"726","option_type":"hundred","option_generate":"10","difficulty":"3"},{"id":"230632","question":"832","answer":"832","option_type":"hundred","option_generate":"10","difficulty":"3"},{"id":"230518","question":"718","answer":"718","option_type":"hundred","option_generate":"10","difficulty":"3"}]}}